[
  {
    "name": "Dekko Fruit Funda Soft Drink Powder Orange",
    "url": "https://eggyolk.chaldal.com/api/Picture/Raw?pictureId=186987"
  },
  {
    "name": "Dekko Fruit Funda Mango Instant Drink Powder",
    "url": "https://eggyolk.chaldal.com/api/Picture/Raw?pictureId=187023"
  },
  {
    "name": "Dekko Fruit Funda Soft Drink Powder Mango Free Orange Drink Powder 125 gm",
    "url": "https://eggyolk.chaldal.com/api/Picture/Raw?pictureId=186988"
  },
  {
    "name": "Hamdard Amrupali Fruit Syrup",
    "url": "https://eggyolk.chaldal.com/api/Picture/Raw?pictureId=186572"
  },
  {
    "name": "Standard Horlicks Health And Nutrition Drink Jar",
    "url": "https://eggyolk.chaldal.com/api/Picture/Raw?pictureId=163368"
  },
  {
    "name": "Dekko Fruit Funda Soft Drink Powder Orange",
    "url": "https://eggyolk.chaldal.com/api/Picture/Raw?pictureId=186986"
  },
  {
    "name": "Dekko Fruit Funda Soft Drink Powder Mango",
    "url": "https://eggyolk.chaldal.com/api/Picture/Raw?pictureId=186985"
  },
  {
    "name": "Horlicks Chocolate Flavour Jar",
    "url": "https://eggyolk.chaldal.com/api/Picture/Raw?pictureId=163350"
  },
  {
    "name": "Maltova Health And Nutrition Drink BIB",
    "url": "https://eggyolk.chaldal.com/api/Picture/Raw?pictureId=128292"
  },
  {
    "name": "ISPI Mango Instant Powder Drink",
    "url": "https://eggyolk.chaldal.com/api/Picture/Raw?pictureId=169984"
  },
  {
    "name": "ISPI Orange Instant Powder Drink",
    "url": "https://eggyolk.chaldal.com/api/Picture/Raw?pictureId=169985"
  },
  {
    "name": "Mothers Horlicks Health and Nutrition Drink BIB",
    "url": "https://eggyolk.chaldal.com/api/Picture/Raw?pictureId=128293"
  },
  {
    "name": "Tang Orange Flavoured Instant Drink Powder Jar",
    "url": "https://eggyolk.chaldal.com/api/Picture/Raw?pictureId=157572"
  },
  {
    "name": "ISPI Orange Instant Powder Drink",
    "url": "https://eggyolk.chaldal.com/api/Picture/Raw?pictureId=169986"
  },
  {
    "name": "Tang Orange Instant Drink Powder BIB",
    "url": "https://eggyolk.chaldal.com/api/Picture/Raw?pictureId=129382"
  },
  {
    "name": "Tang Orange Instant Drink Powder BIB",
    "url": "https://eggyolk.chaldal.com/api/Picture/Raw?pictureId=169511"
  },
  {
    "name": "Tang Mango Instant Drink Powder BIB",
    "url": "https://eggyolk.chaldal.com/api/Picture/Raw?pictureId=169218"
  },
  {
    "name": "ISPI Mango Instant Powder Drink",
    "url": "https://eggyolk.chaldal.com/api/Picture/Raw?pictureId=169983"
  },
  {
    "name": "Tang Mango Flavoured Instant Drink Powder Jar",
    "url": "https://eggyolk.chaldal.com/api/Picture/Raw?pictureId=157573"
  },
  {
    "name": "Nestle Milo Activ-Go Chocolate Powder Drink Box",
    "url": "https://eggyolk.chaldal.com/api/Picture/Raw?pictureId=146682"
  },
  {
    "name": "Tang Mango Instant Drink Powder BIB",
    "url": "https://eggyolk.chaldal.com/api/Picture/Raw?pictureId=169510"
  },
  {
    "name": "Tang Orange Instant Drink Powder BIB",
    "url": "https://eggyolk.chaldal.com/api/Picture/Raw?pictureId=136046"
  },
  {
    "name": "Shokti Orange Soft Drinks Powder",
    "url": "https://eggyolk.chaldal.com/api/Picture/Raw?pictureId=168319"
  },
  {
    "name": "Shokti Mango Soft Drinks Powder",
    "url": "https://eggyolk.chaldal.com/api/Picture/Raw?pictureId=168318"
  },
  {
    "name": "Foster Clarks Pineapple Instant Drink Powder",
    "url": "https://eggyolk.chaldal.com/api/Picture/Raw?pictureId=129814"
  },
  {
    "name": "Tang Orange Flavoured Instant Drink Powder Tub",
    "url": "https://eggyolk.chaldal.com/api/Picture/Raw?pictureId=157574"
  },
  {
    "name": "Tang Mango Flavoured Instant Drink Powder Tub",
    "url": "https://eggyolk.chaldal.com/api/Picture/Raw?pictureId=153841"
  },
  {
    "name": "Nutri Juicee Orange Fortified Soft Drink Powder",
    "url": "https://eggyolk.chaldal.com/api/Picture/Raw?pictureId=169518"
  },
  {
    "name": "Nutri Juicee Mango Fortified Soft Drink Powder",
    "url": "https://eggyolk.chaldal.com/api/Picture/Raw?pictureId=127275"
  },
  {
    "name": "Foster Clarks Mango Instant Drink Powder",
    "url": "https://eggyolk.chaldal.com/api/Picture/Raw?pictureId=128582"
  },
  {
    "name": "American Garden Pancake Syrup Original",
    "url": "https://eggyolk.chaldal.com/api/Picture/Raw?pictureId=177293"
  },
  {
    "name": "Junior Horlicks Health And Nutrition Drink Container Stage-2",
    "url": "https://eggyolk.chaldal.com/api/Picture/Raw?pictureId=168999"
  },
  {
    "name": "Standard Horlicks Health And Nutrition Drink Jar",
    "url": "https://eggyolk.chaldal.com/api/Picture/Raw?pictureId=163370"
  },
  {
    "name": "Country Time Pink lemonade Powder Drink",
    "url": "https://eggyolk.chaldal.com/api/Picture/Raw?pictureId=60535"
  },
  {
    "name": "Country Time lemonade Powder Drink",
    "url": "https://eggyolk.chaldal.com/api/Picture/Raw?pictureId=60536"
  },
  {
    "name": "Ovaltine Power 10 Chocolate Drink Jar",
    "url": "https://eggyolk.chaldal.com/api/Picture/Raw?pictureId=131786"
  },
  {
    "name": "Boost Chocolate Jar",
    "url": "https://eggyolk.chaldal.com/api/Picture/Raw?pictureId=173037"
  },
  {
    "name": "ISPI Mango Instant Powder Drink",
    "url": "https://eggyolk.chaldal.com/api/Picture/Raw?pictureId=169982"
  },
  {
    "name": "Hersheys Strawberry Syrup",
    "url": "https://eggyolk.chaldal.com/api/Picture/Raw?pictureId=174494"
  },
  {
    "name": "Hersheys Chocolate Syrup",
    "url": "https://eggyolk.chaldal.com/api/Picture/Raw?pictureId=103086"
  },
  {
    "name": "Womens Plus Horlicks Health And Nutrition Drink Jar",
    "url": "https://eggyolk.chaldal.com/api/Picture/Raw?pictureId=128374"
  },
  {
    "name": "Horlicks Lite Health And Nutrition Drink Jar",
    "url": "https://eggyolk.chaldal.com/api/Picture/Raw?pictureId=155022"
  },
  {
    "name": "Foster Clarks Pineapple Instant Drink Powder",
    "url": "https://eggyolk.chaldal.com/api/Picture/Raw?pictureId=153895"
  },
  {
    "name": "Foster Clarks Mango Instant Drink Powder",
    "url": "https://eggyolk.chaldal.com/api/Picture/Raw?pictureId=128583"
  },
  {
    "name": "Foster Clarks Mandarin Instant Drink Powder",
    "url": "https://eggyolk.chaldal.com/api/Picture/Raw?pictureId=45990"
  },
  {
    "name": "Prome Mango Powder Drink",
    "url": "https://eggyolk.chaldal.com/api/Picture/Raw?pictureId=179380"
  },
  {
    "name": "Hersheys Caramel Syrup",
    "url": "https://eggyolk.chaldal.com/api/Picture/Raw?pictureId=103085"
  }
]